multibase_f_tyulpin/__init__.py
multibase_f_tyulpin/multibase_f_tyulpin.py
multibase_f_tyulpin/tests.py
multibase_f_tyulpin-1.0.dist-info/METADATA
multibase_f_tyulpin-1.0.dist-info/WHEEL
multibase_f_tyulpin-1.0.dist-info/top_level.txt
multibase_f_tyulpin-1.0.dist-info/RECORD
