Metadata-Version: 2.4
Name: multibase_f_tyulpin
Version: 1.0
Summary: A Python module for converting numbers between numeral systems (2-36) and evaluating cross-base mathematical expressions.
Author: Fedor Tyulpin
Author-email: f.tyulpin@gmail.com
Keywords: converting numbers numeral systems
Classifier: Programming Language :: Python :: 3.11
Classifier: Operating System :: OS Independent
Requires-Python: >=3.6
Dynamic: author
Dynamic: author-email
Dynamic: classifier
Dynamic: description
Dynamic: description-content-type
Dynamic: keywords
Dynamic: requires-python
Dynamic: summary
